pydstools/__init__.py
pydstools/digsilent_simulation.py
pydstools/dstools.py
pydstools/dynamics.py
pydstools-0.1.0.dist-info/COPYING
pydstools-0.1.0.dist-info/LICENSE
pydstools-0.1.0.dist-info/WHEEL
pydstools-0.1.0.dist-info/METADATA
pydstools-0.1.0.dist-info/RECORD
