Metadata-Version: 2.1
Name: pydstools
Version: 0.1.0
Summary: =========
Home-page: UNKNOWN
License: UNKNOWN
Author: Juan Manuel Mauricio
Author-email: jmmauricio6@gmail.com
Classifier: License :: OSI Approved :: MIT License
